{
    "cookie-59": [
        {
            "patient_id": "cookie-59",
            "patient_name": "little truth",
            "operator_name": "frosty truth",
            "patient_gender": "F",
            "physician_reading": "Dr. broad grass",
            "physician_referring": "Dr. cool rain"
        }
    ],
    "cookie-16": [
        {
            "patient_id": "cookie-16",
            "patient_name": "broad violet",
            "operator_name": "aged paper",
            "patient_gender": "F",
            "physician_reading": "Dr. young dawn",
            "physician_referring": "Dr. patient silence"
        }
    ],
    "cookie-32": [
        {
            "patient_id": "cookie-32",
            "patient_name": "plain hall",
            "operator_name": "quiet sun",
            "patient_gender": "F",
            "physician_reading": "Dr. delicate darkness",
            "physician_referring": "Dr. delicate rain"
        }
    ],
    "cookie-41": [
        {
            "patient_id": "cookie-41",
            "patient_name": "summer fog",
            "operator_name": "quiet sun",
            "patient_gender": "M",
            "physician_reading": "Dr. fragrant scene",
            "physician_referring": "Dr. solitary shadow"
        },
        {
            "patient_id": "cookie-41",
            "patient_name": "summer fog",
            "operator_name": "blue salad",
            "patient_gender": "M",
            "physician_reading": "Dr. noisy shape",
            "physician_referring": "Dr. frosty king"
        },
        {
            "patient_id": "cookie-41",
            "patient_name": "summer fog",
            "operator_name": "tight salad",
            "patient_gender": "M",
            "physician_reading": "Dr. autumn credit",
            "physician_referring": "Dr. twilight bird"
        },
        {
            "patient_id": "cookie-41",
            "patient_name": "summer fog",
            "operator_name": "square glade",
            "patient_gender": "M",
            "physician_reading": "Dr. falling shape",
            "physician_referring": "Dr. dry water"
        },
        {
            "patient_id": "cookie-41",
            "patient_name": "summer fog",
            "operator_name": "steep frog",
            "patient_gender": "M",
            "physician_reading": "Dr. young waterfall",
            "physician_referring": "Dr. broad tree"
        },
        {
            "patient_id": "cookie-41",
            "patient_name": "summer fog",
            "operator_name": "silent sky",
            "patient_gender": "M",
            "physician_reading": "Dr. jolly glitter",
            "physician_referring": "Dr. rough tooth"
        },
        {
            "patient_id": "cookie-41",
            "patient_name": "summer fog",
            "operator_name": "bitter grass",
            "patient_gender": "M",
            "physician_reading": "Dr. muddy star",
            "physician_referring": "Dr. shy brook"
        },
        {
            "patient_id": "cookie-41",
            "patient_name": "summer fog",
            "operator_name": "old unit",
            "patient_gender": "M",
            "physician_reading": "Dr. raspy tree",
            "physician_referring": "Dr. dawn bread"
        },
        {
            "patient_id": "cookie-41",
            "patient_name": "summer fog",
            "operator_name": "yellow base",
            "patient_gender": "M",
            "physician_reading": "Dr. old wind",
            "physician_referring": "Dr. silent hall"
        },
        {
            "patient_id": "cookie-41",
            "patient_name": "summer fog",
            "operator_name": "polished fire",
            "patient_gender": "M",
            "physician_reading": "Dr. wild dream",
            "physician_referring": "Dr. old unit"
        }
    ],
    "cookie-33": [
        {
            "patient_id": "cookie-33",
            "patient_name": "wild forest",
            "operator_name": "square smoke",
            "patient_gender": "M",
            "physician_reading": "Dr. solitary sun",
            "physician_referring": "Dr. white leaf"
        }
    ],
    "cookie-3": [
        {
            "patient_id": "cookie-3",
            "patient_name": "noisy moon",
            "operator_name": "curly credit",
            "patient_gender": "F",
            "physician_reading": "Dr. yellow band",
            "physician_referring": "Dr. blue shape"
        }
    ],
    "cookie-22": [
        {
            "patient_id": "cookie-22",
            "patient_name": "floral dawn",
            "operator_name": "small hill",
            "patient_gender": "F",
            "physician_reading": "Dr. muddy night",
            "physician_referring": "Dr. ancient haze"
        }
    ],
    "cookie-23": [
        {
            "patient_id": "cookie-23",
            "patient_name": "polished dream",
            "operator_name": "rapid resonance",
            "patient_gender": "M",
            "physician_reading": "Dr. lingering art",
            "physician_referring": "Dr. autumn rain"
        }
    ],
    "cookie-61": [
        {
            "patient_id": "cookie-61",
            "patient_name": "calm star",
            "operator_name": "withered term",
            "patient_gender": "M",
            "physician_reading": "Dr. red star",
            "physician_referring": "Dr. hidden hat"
        },
        {
            "patient_id": "cookie-61",
            "patient_name": "calm star",
            "operator_name": "dark tooth",
            "patient_gender": "M",
            "physician_reading": "Dr. jolly queen",
            "physician_referring": "Dr. black grass"
        },
        {
            "patient_id": "cookie-61",
            "patient_name": "calm star",
            "operator_name": "old cherry",
            "patient_gender": "M",
            "physician_reading": "Dr. broken bonus",
            "physician_referring": "Dr. ancient dew"
        },
        {
            "patient_id": "cookie-61",
            "patient_name": "calm star",
            "operator_name": "shiny shadow",
            "patient_gender": "M",
            "physician_reading": "Dr. still violet",
            "physician_referring": "Dr. soft paper"
        },
        {
            "patient_id": "cookie-61",
            "patient_name": "calm star",
            "operator_name": "frosty truth",
            "patient_gender": "M",
            "physician_reading": "Dr. aged unit",
            "physician_referring": "Dr. red salad"
        }
    ],
    "cookie-1": [
        {
            "patient_id": "cookie-1",
            "patient_name": "silent smoke",
            "operator_name": "weathered shape",
            "patient_gender": "F",
            "physician_reading": "Dr. lucky darkness",
            "physician_referring": "Dr. autumn night"
        }
    ],
    "cookie-62": [
        {
            "patient_id": "cookie-62",
            "patient_name": "cool feather",
            "operator_name": "red field",
            "patient_gender": "M",
            "physician_reading": "Dr. tiny river",
            "physician_referring": "Dr. calm star"
        },
        {
            "patient_id": "cookie-62",
            "patient_name": "cool feather",
            "operator_name": "muddy frog",
            "patient_gender": "M",
            "physician_reading": "Dr. crimson recipe",
            "physician_referring": "Dr. throbbing union"
        }
    ],
    "cookie-45": [
        {
            "patient_id": "cookie-45",
            "patient_name": "muddy wind",
            "operator_name": "late snowflake",
            "patient_gender": "F",
            "physician_reading": "Dr. cold rain",
            "physician_referring": "Dr. proud salad"
        },
        {
            "patient_id": "cookie-45",
            "patient_name": "muddy wind",
            "operator_name": "frosty recipe",
            "patient_gender": "F",
            "physician_reading": "Dr. odd sea",
            "physician_referring": "Dr. wild tooth"
        },
        {
            "patient_id": "cookie-45",
            "patient_name": "muddy wind",
            "operator_name": "snowy math",
            "patient_gender": "F",
            "physician_reading": "Dr. nameless surf",
            "physician_referring": "Dr. twilight rice"
        },
        {
            "patient_id": "cookie-45",
            "patient_name": "muddy wind",
            "operator_name": "young mouse",
            "patient_gender": "F",
            "physician_reading": "Dr. jolly wind",
            "physician_referring": "Dr. tiny glade"
        },
        {
            "patient_id": "cookie-45",
            "patient_name": "muddy wind",
            "operator_name": "square cherry",
            "patient_gender": "F",
            "physician_reading": "Dr. raspy darkness",
            "physician_referring": "Dr. old heart"
        },
        {
            "patient_id": "cookie-45",
            "patient_name": "muddy wind",
            "operator_name": "misty king",
            "patient_gender": "F",
            "physician_reading": "Dr. tiny sun",
            "physician_referring": "Dr. delicate sunset"
        }
    ],
    "cookie-10": [
        {
            "patient_id": "cookie-10",
            "patient_name": "broken sun",
            "operator_name": "cold flower",
            "patient_gender": "M",
            "physician_reading": "Dr. little breeze",
            "physician_referring": "Dr. plain cloud"
        },
        {
            "patient_id": "cookie-10",
            "patient_name": "broken sun",
            "operator_name": "empty haze",
            "patient_gender": "M",
            "physician_reading": "Dr. solitary tree",
            "physician_referring": "Dr. soft bread"
        }
    ],
    "cookie-53": [
        {
            "patient_id": "cookie-53",
            "patient_name": "shrill star",
            "operator_name": "lucky hill",
            "patient_gender": "F",
            "physician_reading": "Dr. polished sun",
            "physician_referring": "Dr. rough bush"
        },
        {
            "patient_id": "cookie-53",
            "patient_name": "shrill star",
            "operator_name": "crimson dust",
            "patient_gender": "F",
            "physician_reading": "Dr. fancy morning",
            "physician_referring": "Dr. shy field"
        },
        {
            "patient_id": "cookie-53",
            "patient_name": "shrill star",
            "operator_name": "steep poetry",
            "patient_gender": "F",
            "physician_reading": "Dr. icy darkness",
            "physician_referring": "Dr. quiet morning"
        },
        {
            "patient_id": "cookie-53",
            "patient_name": "shrill star",
            "operator_name": "muddy darkness",
            "patient_gender": "F",
            "physician_reading": "Dr. delicate thunder",
            "physician_referring": "Dr. round resonance"
        },
        {
            "patient_id": "cookie-53",
            "patient_name": "shrill star",
            "operator_name": "falling sea",
            "patient_gender": "F",
            "physician_reading": "Dr. small block",
            "physician_referring": "Dr. fancy firefly"
        }
    ],
    "cookie-64": [
        {
            "patient_id": "cookie-64",
            "patient_name": "soft wood",
            "operator_name": "lively leaf",
            "patient_gender": "M",
            "physician_reading": "Dr. rapid sun",
            "physician_referring": "Dr. young truth"
        },
        {
            "patient_id": "cookie-64",
            "patient_name": "soft wood",
            "operator_name": "morning lab",
            "patient_gender": "M",
            "physician_reading": "Dr. cold wind",
            "physician_referring": "Dr. gentle morning"
        },
        {
            "patient_id": "cookie-64",
            "patient_name": "soft wood",
            "operator_name": "solitary hat",
            "patient_gender": "M",
            "physician_reading": "Dr. broken mouse",
            "physician_referring": "Dr. snowy grass"
        },
        {
            "patient_id": "cookie-64",
            "patient_name": "soft wood",
            "operator_name": "shy pine",
            "patient_gender": "M",
            "physician_reading": "Dr. weathered unit",
            "physician_referring": "Dr. bold morning"
        },
        {
            "patient_id": "cookie-64",
            "patient_name": "soft wood",
            "operator_name": "throbbing darkness",
            "patient_gender": "M",
            "physician_reading": "Dr. throbbing term",
            "physician_referring": "Dr. soft night"
        },
        {
            "patient_id": "cookie-64",
            "patient_name": "soft wood",
            "operator_name": "snowy rain",
            "patient_gender": "M",
            "physician_reading": "Dr. withered breeze",
            "physician_referring": "Dr. orange bonus"
        },
        {
            "patient_id": "cookie-64",
            "patient_name": "soft wood",
            "operator_name": "late shape",
            "patient_gender": "M",
            "physician_reading": "Dr. broad art",
            "physician_referring": "Dr. cold morning"
        },
        {
            "patient_id": "cookie-64",
            "patient_name": "soft wood",
            "operator_name": "aged hat",
            "patient_gender": "M",
            "physician_reading": "Dr. billowing wood",
            "physician_referring": "Dr. floral rice"
        }
    ],
    "cookie-28": [
        {
            "patient_id": "cookie-28",
            "patient_name": "lively firefly",
            "operator_name": "lucky flower",
            "patient_gender": "M",
            "physician_reading": "Dr. lively mountain",
            "physician_referring": "Dr. square disk"
        }
    ],
    "cookie-54": [
        {
            "patient_id": "cookie-54",
            "patient_name": "odd bread",
            "operator_name": "lingering bread",
            "patient_gender": "M",
            "physician_reading": "Dr. twilight math",
            "physician_referring": "Dr. frosty lake"
        },
        {
            "patient_id": "cookie-54",
            "patient_name": "odd bread",
            "operator_name": "flat art",
            "patient_gender": "M",
            "physician_reading": "Dr. nameless grass",
            "physician_referring": "Dr. rough heart"
        },
        {
            "patient_id": "cookie-54",
            "patient_name": "odd bread",
            "operator_name": "lively thunder",
            "patient_gender": "M",
            "physician_reading": "Dr. polished pond",
            "physician_referring": "Dr. square thunder"
        },
        {
            "patient_id": "cookie-54",
            "patient_name": "odd bread",
            "operator_name": "divine block",
            "patient_gender": "M",
            "physician_reading": "Dr. orange dawn",
            "physician_referring": "Dr. calm resonance"
        },
        {
            "patient_id": "cookie-54",
            "patient_name": "odd bread",
            "operator_name": "round math",
            "patient_gender": "M",
            "physician_reading": "Dr. rough frog",
            "physician_referring": "Dr. raspy paper"
        }
    ],
    "cookie-11": [
        {
            "patient_id": "cookie-11",
            "patient_name": "damp king",
            "operator_name": "empty salad",
            "patient_gender": "F",
            "physician_reading": "Dr. noisy feather",
            "physician_referring": "Dr. broad mouse"
        },
        {
            "patient_id": "cookie-11",
            "patient_name": "damp king",
            "operator_name": "crimson darkness",
            "patient_gender": "F",
            "physician_reading": "Dr. small wood",
            "physician_referring": "Dr. crimson resonance"
        }
    ],
    "cookie-7": [
        {
            "patient_id": "cookie-7",
            "patient_name": "falling shadow",
            "operator_name": "delicate mud",
            "patient_gender": "M",
            "physician_reading": "Dr. round river",
            "physician_referring": "Dr. autumn star"
        }
    ],
    "cookie-4": [
        {
            "patient_id": "cookie-4",
            "patient_name": "floral cell",
            "operator_name": "tiny hill",
            "patient_gender": "M",
            "physician_reading": "Dr. sweet bar",
            "physician_referring": "Dr. polished field"
        }
    ],
    "cookie-12": [
        {
            "patient_id": "cookie-12",
            "patient_name": "bold lake",
            "operator_name": "frosty thunder",
            "patient_gender": "F",
            "physician_reading": "Dr. orange violet",
            "physician_referring": "Dr. round credit"
        }
    ],
    "cookie-25": [
        {
            "patient_id": "cookie-25",
            "patient_name": "wispy math",
            "operator_name": "ancient sea",
            "patient_gender": "F",
            "physician_reading": "Dr. orange firefly",
            "physician_referring": "Dr. restless wood"
        }
    ],
    "cookie-51": [
        {
            "patient_id": "cookie-51",
            "patient_name": "small meadow",
            "operator_name": "green base",
            "patient_gender": "F",
            "physician_reading": "Dr. icy dust",
            "physician_referring": "Dr. holy art"
        },
        {
            "patient_id": "cookie-51",
            "patient_name": "small meadow",
            "operator_name": "autumn night",
            "patient_gender": "F",
            "physician_reading": "Dr. billowing shadow",
            "physician_referring": "Dr. twilight surf"
        },
        {
            "patient_id": "cookie-51",
            "patient_name": "small meadow",
            "operator_name": "plain recipe",
            "patient_gender": "F",
            "physician_reading": "Dr. raspy paper",
            "physician_referring": "Dr. wandering wave"
        },
        {
            "patient_id": "cookie-51",
            "patient_name": "small meadow",
            "operator_name": "empty recipe",
            "patient_gender": "F",
            "physician_reading": "Dr. late cake",
            "physician_referring": "Dr. green cherry"
        },
        {
            "patient_id": "cookie-51",
            "patient_name": "small meadow",
            "operator_name": "rapid brook",
            "patient_gender": "F",
            "physician_reading": "Dr. nameless limit",
            "physician_referring": "Dr. red fog"
        },
        {
            "patient_id": "cookie-51",
            "patient_name": "small meadow",
            "operator_name": "jolly snowflake",
            "patient_gender": "F",
            "physician_reading": "Dr. delicate poetry",
            "physician_referring": "Dr. aged star"
        },
        {
            "patient_id": "cookie-51",
            "patient_name": "small meadow",
            "operator_name": "lucky lake",
            "patient_gender": "F",
            "physician_reading": "Dr. small glade",
            "physician_referring": "Dr. rapid lake"
        }
    ],
    "cookie-19": [
        {
            "patient_id": "cookie-19",
            "patient_name": "wild shadow",
            "operator_name": "mute sound",
            "patient_gender": "M",
            "physician_reading": "Dr. late bread",
            "physician_referring": "Dr. cool thunder"
        }
    ],
    "cookie-46": [
        {
            "patient_id": "cookie-46",
            "patient_name": "late river",
            "operator_name": "late frog",
            "patient_gender": "M",
            "physician_reading": "Dr. jolly boat",
            "physician_referring": "Dr. jolly bar"
        },
        {
            "patient_id": "cookie-46",
            "patient_name": "late river",
            "operator_name": "steep dew",
            "patient_gender": "M",
            "physician_reading": "Dr. cold truth",
            "physician_referring": "Dr. odd water"
        },
        {
            "patient_id": "cookie-46",
            "patient_name": "late river",
            "operator_name": "tight dust",
            "patient_gender": "M",
            "physician_reading": "Dr. raspy bonus",
            "physician_referring": "Dr. round snow"
        },
        {
            "patient_id": "cookie-46",
            "patient_name": "late river",
            "operator_name": "bold disk",
            "patient_gender": "M",
            "physician_reading": "Dr. aged wave",
            "physician_referring": "Dr. snowy shadow"
        },
        {
            "patient_id": "cookie-46",
            "patient_name": "late river",
            "operator_name": "lucky lab",
            "patient_gender": "M",
            "physician_reading": "Dr. billowing salad",
            "physician_referring": "Dr. summer heart"
        },
        {
            "patient_id": "cookie-46",
            "patient_name": "late river",
            "operator_name": "falling fire",
            "patient_gender": "M",
            "physician_reading": "Dr. frosty morning",
            "physician_referring": "Dr. wispy mouse"
        },
        {
            "patient_id": "cookie-46",
            "patient_name": "late river",
            "operator_name": "broad water",
            "patient_gender": "M",
            "physician_reading": "Dr. round wind",
            "physician_referring": "Dr. mute shadow"
        }
    ],
    "cookie-30": [
        {
            "patient_id": "cookie-30",
            "patient_name": "withered math",
            "operator_name": "nameless star",
            "patient_gender": "M",
            "physician_reading": "Dr. small term",
            "physician_referring": "Dr. sparkling block"
        }
    ],
    "cookie-60": [
        {
            "patient_id": "cookie-60",
            "patient_name": "snowy forest",
            "operator_name": "flat surf",
            "patient_gender": "F",
            "physician_reading": "Dr. royal recipe",
            "physician_referring": "Dr. nameless mud"
        },
        {
            "patient_id": "cookie-60",
            "patient_name": "snowy forest",
            "operator_name": "green sunset",
            "patient_gender": "F",
            "physician_reading": "Dr. empty shape",
            "physician_referring": "Dr. small glitter"
        },
        {
            "patient_id": "cookie-60",
            "patient_name": "snowy forest",
            "operator_name": "cool dust",
            "patient_gender": "F",
            "physician_reading": "Dr. wispy rain",
            "physician_referring": "Dr. empty resonance"
        },
        {
            "patient_id": "cookie-60",
            "patient_name": "snowy forest",
            "operator_name": "fragrant block",
            "patient_gender": "F",
            "physician_reading": "Dr. white rain",
            "physician_referring": "Dr. green tooth"
        },
        {
            "patient_id": "cookie-60",
            "patient_name": "snowy forest",
            "operator_name": "solitary shadow",
            "patient_gender": "F",
            "physician_reading": "Dr. solitary fire",
            "physician_referring": "Dr. damp hat"
        }
    ],
    "cookie-20": [
        {
            "patient_id": "cookie-20",
            "patient_name": "delicate unit",
            "operator_name": "empty moon",
            "patient_gender": "M",
            "physician_reading": "Dr. misty truth",
            "physician_referring": "Dr. royal dust"
        }
    ],
    "cookie-67": [
        {
            "patient_id": "cookie-67",
            "patient_name": "lucky brook",
            "operator_name": "restless feather",
            "patient_gender": "F",
            "physician_reading": "Dr. dawn cake",
            "physician_referring": "Dr. crimson darkness"
        },
        {
            "patient_id": "cookie-67",
            "patient_name": "lucky brook",
            "operator_name": "bold rain",
            "patient_gender": "F",
            "physician_reading": "Dr. black credit",
            "physician_referring": "Dr. billowing cherry"
        }
    ],
    "cookie-66": [
        {
            "patient_id": "cookie-66",
            "patient_name": "broken hill",
            "operator_name": "empty night",
            "patient_gender": "M",
            "physician_reading": "Dr. misty limit",
            "physician_referring": "Dr. nameless tooth"
        },
        {
            "patient_id": "cookie-66",
            "patient_name": "broken hill",
            "operator_name": "crimson dream",
            "patient_gender": "M",
            "physician_reading": "Dr. rapid cake",
            "physician_referring": "Dr. gentle silence"
        },
        {
            "patient_id": "cookie-66",
            "patient_name": "broken hill",
            "operator_name": "autumn resonance",
            "patient_gender": "M",
            "physician_reading": "Dr. lingering hall",
            "physician_referring": "Dr. autumn dawn"
        }
    ],
    "cookie-29": [
        {
            "patient_id": "cookie-29",
            "patient_name": "quiet truth",
            "operator_name": "super rain",
            "patient_gender": "M",
            "physician_reading": "Dr. super base",
            "physician_referring": "Dr. proud sound"
        }
    ],
    "cookie-50": [
        {
            "patient_id": "cookie-50",
            "patient_name": "lucky silence",
            "operator_name": "mute resonance",
            "patient_gender": "M",
            "physician_reading": "Dr. autumn block",
            "physician_referring": "Dr. falling mud"
        },
        {
            "patient_id": "cookie-50",
            "patient_name": "lucky silence",
            "operator_name": "white hat",
            "patient_gender": "M",
            "physician_reading": "Dr. patient salad",
            "physician_referring": "Dr. billowing rain"
        },
        {
            "patient_id": "cookie-50",
            "patient_name": "lucky silence",
            "operator_name": "dry bird",
            "patient_gender": "M",
            "physician_reading": "Dr. jolly pond",
            "physician_referring": "Dr. frosty wood"
        },
        {
            "patient_id": "cookie-50",
            "patient_name": "lucky silence",
            "operator_name": "wispy pond",
            "patient_gender": "M",
            "physician_reading": "Dr. green bird",
            "physician_referring": "Dr. purple dew"
        },
        {
            "patient_id": "cookie-50",
            "patient_name": "lucky silence",
            "operator_name": "weathered truth",
            "patient_gender": "M",
            "physician_reading": "Dr. withered snow",
            "physician_referring": "Dr. late cell"
        },
        {
            "patient_id": "cookie-50",
            "patient_name": "lucky silence",
            "operator_name": "falling dream",
            "patient_gender": "M",
            "physician_reading": "Dr. green queen",
            "physician_referring": "Dr. frosty frog"
        },
        {
            "patient_id": "cookie-50",
            "patient_name": "lucky silence",
            "operator_name": "jolly hill",
            "patient_gender": "M",
            "physician_reading": "Dr. royal sun",
            "physician_referring": "Dr. winter pond"
        },
        {
            "patient_id": "cookie-50",
            "patient_name": "lucky silence",
            "operator_name": "late grass",
            "patient_gender": "M",
            "physician_reading": "Dr. polished mouse",
            "physician_referring": "Dr. blue shadow"
        },
        {
            "patient_id": "cookie-50",
            "patient_name": "lucky silence",
            "operator_name": "rapid poetry",
            "patient_gender": "M",
            "physician_reading": "Dr. dawn butterfly",
            "physician_referring": "Dr. silent voice"
        },
        {
            "patient_id": "cookie-50",
            "patient_name": "lucky silence",
            "operator_name": "shrill hill",
            "patient_gender": "M",
            "physician_reading": "Dr. empty voice",
            "physician_referring": "Dr. curly bush"
        }
    ],
    "cookie-42": [
        {
            "patient_id": "cookie-42",
            "patient_name": "cool field",
            "operator_name": "shiny boat",
            "patient_gender": "M",
            "physician_reading": "Dr. summer sky",
            "physician_referring": "Dr. rough bread"
        },
        {
            "patient_id": "cookie-42",
            "patient_name": "cool field",
            "operator_name": "curly tree",
            "patient_gender": "M",
            "physician_reading": "Dr. fancy dawn",
            "physician_referring": "Dr. snowy frog"
        },
        {
            "patient_id": "cookie-42",
            "patient_name": "cool field",
            "operator_name": "old feather",
            "patient_gender": "M",
            "physician_reading": "Dr. sweet field",
            "physician_referring": "Dr. fragrant flower"
        },
        {
            "patient_id": "cookie-42",
            "patient_name": "cool field",
            "operator_name": "orange glitter",
            "patient_gender": "M",
            "physician_reading": "Dr. billowing thunder",
            "physician_referring": "Dr. young water"
        },
        {
            "patient_id": "cookie-42",
            "patient_name": "cool field",
            "operator_name": "polished snowflake",
            "patient_gender": "M",
            "physician_reading": "Dr. icy dust",
            "physician_referring": "Dr. red cake"
        },
        {
            "patient_id": "cookie-42",
            "patient_name": "cool field",
            "operator_name": "morning recipe",
            "patient_gender": "M",
            "physician_reading": "Dr. lucky cell",
            "physician_referring": "Dr. bold tooth"
        },
        {
            "patient_id": "cookie-42",
            "patient_name": "cool field",
            "operator_name": "sparkling mud",
            "patient_gender": "M",
            "physician_reading": "Dr. ancient leaf",
            "physician_referring": "Dr. weathered feather"
        },
        {
            "patient_id": "cookie-42",
            "patient_name": "cool field",
            "operator_name": "throbbing union",
            "patient_gender": "M",
            "physician_reading": "Dr. small wood",
            "physician_referring": "Dr. patient haze"
        },
        {
            "patient_id": "cookie-42",
            "patient_name": "cool field",
            "operator_name": "steep mud",
            "patient_gender": "M",
            "physician_reading": "Dr. icy cell",
            "physician_referring": "Dr. billowing forest"
        },
        {
            "patient_id": "cookie-42",
            "patient_name": "cool field",
            "operator_name": "odd star",
            "patient_gender": "M",
            "physician_reading": "Dr. small sound",
            "physician_referring": "Dr. damp sky"
        },
        {
            "patient_id": "cookie-42",
            "patient_name": "cool field",
            "operator_name": "plain sound",
            "patient_gender": "M",
            "physician_reading": "Dr. square sea",
            "physician_referring": "Dr. super cherry"
        },
        {
            "patient_id": "cookie-42",
            "patient_name": "cool field",
            "operator_name": "misty boat",
            "patient_gender": "M",
            "physician_reading": "Dr. misty base",
            "physician_referring": "Dr. purple truth"
        }
    ],
    "cookie-68": [
        {
            "patient_id": "cookie-68",
            "patient_name": "divine frog",
            "operator_name": "bold glade",
            "patient_gender": "M",
            "physician_reading": "Dr. lingering butterfly",
            "physician_referring": "Dr. throbbing pond"
        },
        {
            "patient_id": "cookie-68",
            "patient_name": "divine frog",
            "operator_name": "lingering art",
            "patient_gender": "M",
            "physician_reading": "Dr. snowy wind",
            "physician_referring": "Dr. lively wildflower"
        },
        {
            "patient_id": "cookie-68",
            "patient_name": "divine frog",
            "operator_name": "frosty brook",
            "patient_gender": "M",
            "physician_reading": "Dr. aged shadow",
            "physician_referring": "Dr. broken boat"
        },
        {
            "patient_id": "cookie-68",
            "patient_name": "divine frog",
            "operator_name": "crimson breeze",
            "patient_gender": "M",
            "physician_reading": "Dr. damp bird",
            "physician_referring": "Dr. hidden bar"
        }
    ],
    "cookie-58": [
        {
            "patient_id": "cookie-58",
            "patient_name": "lively bird",
            "operator_name": "summer cloud",
            "patient_gender": "F",
            "physician_reading": "Dr. throbbing tooth",
            "physician_referring": "Dr. weathered wind"
        },
        {
            "patient_id": "cookie-58",
            "patient_name": "lively bird",
            "operator_name": "tight queen",
            "patient_gender": "F",
            "physician_reading": "Dr. solitary snow",
            "physician_referring": "Dr. morning shape"
        },
        {
            "patient_id": "cookie-58",
            "patient_name": "lively bird",
            "operator_name": "flat math",
            "patient_gender": "F",
            "physician_reading": "Dr. patient surf",
            "physician_referring": "Dr. purple hill"
        },
        {
            "patient_id": "cookie-58",
            "patient_name": "lively bird",
            "operator_name": "quiet recipe",
            "patient_gender": "F",
            "physician_reading": "Dr. royal wind",
            "physician_referring": "Dr. royal morning"
        },
        {
            "patient_id": "cookie-58",
            "patient_name": "lively bird",
            "operator_name": "lingering shadow",
            "patient_gender": "F",
            "physician_reading": "Dr. hidden unit",
            "physician_referring": "Dr. icy math"
        },
        {
            "patient_id": "cookie-58",
            "patient_name": "lively bird",
            "operator_name": "dark boat",
            "patient_gender": "F",
            "physician_reading": "Dr. hidden recipe",
            "physician_referring": "Dr. tiny river"
        },
        {
            "patient_id": "cookie-58",
            "patient_name": "lively bird",
            "operator_name": "round breeze",
            "patient_gender": "F",
            "physician_reading": "Dr. holy grass",
            "physician_referring": "Dr. long bread"
        },
        {
            "patient_id": "cookie-58",
            "patient_name": "lively bird",
            "operator_name": "green term",
            "patient_gender": "F",
            "physician_reading": "Dr. lingering butterfly",
            "physician_referring": "Dr. frosty wildflower"
        },
        {
            "patient_id": "cookie-58",
            "patient_name": "lively bird",
            "operator_name": "icy silence",
            "patient_gender": "F",
            "physician_reading": "Dr. rapid wildflower",
            "physician_referring": "Dr. small base"
        },
        {
            "patient_id": "cookie-58",
            "patient_name": "lively bird",
            "operator_name": "gentle frost",
            "patient_gender": "F",
            "physician_reading": "Dr. still hall",
            "physician_referring": "Dr. raspy meadow"
        }
    ],
    "cookie-18": [
        {
            "patient_id": "cookie-18",
            "patient_name": "silent glade",
            "operator_name": "lucky wave",
            "patient_gender": "F",
            "physician_reading": "Dr. cool hill",
            "physician_referring": "Dr. rough wave"
        }
    ],
    "cookie-56": [
        {
            "patient_id": "cookie-56",
            "patient_name": "fancy tooth",
            "operator_name": "patient heart",
            "patient_gender": "M",
            "physician_reading": "Dr. flat bird",
            "physician_referring": "Dr. ancient tooth"
        },
        {
            "patient_id": "cookie-56",
            "patient_name": "fancy tooth",
            "operator_name": "delicate shadow",
            "patient_gender": "M",
            "physician_reading": "Dr. dawn tree",
            "physician_referring": "Dr. floral glitter"
        },
        {
            "patient_id": "cookie-56",
            "patient_name": "fancy tooth",
            "operator_name": "solitary hall",
            "patient_gender": "M",
            "physician_reading": "Dr. dark fire",
            "physician_referring": "Dr. white wind"
        },
        {
            "patient_id": "cookie-56",
            "patient_name": "fancy tooth",
            "operator_name": "winter sea",
            "patient_gender": "M",
            "physician_reading": "Dr. soft snow",
            "physician_referring": "Dr. morning rice"
        },
        {
            "patient_id": "cookie-56",
            "patient_name": "fancy tooth",
            "operator_name": "round river",
            "patient_gender": "M",
            "physician_reading": "Dr. weathered hat",
            "physician_referring": "Dr. wandering wildflower"
        },
        {
            "patient_id": "cookie-56",
            "patient_name": "fancy tooth",
            "operator_name": "frosty breeze",
            "patient_gender": "M",
            "physician_reading": "Dr. still moon",
            "physician_referring": "Dr. raspy bar"
        },
        {
            "patient_id": "cookie-56",
            "patient_name": "fancy tooth",
            "operator_name": "rough hill",
            "patient_gender": "M",
            "physician_reading": "Dr. nameless salad",
            "physician_referring": "Dr. flat fog"
        },
        {
            "patient_id": "cookie-56",
            "patient_name": "fancy tooth",
            "operator_name": "quiet grass",
            "patient_gender": "M",
            "physician_reading": "Dr. hidden resonance",
            "physician_referring": "Dr. wispy wave"
        },
        {
            "patient_id": "cookie-56",
            "patient_name": "fancy tooth",
            "operator_name": "crimson river",
            "patient_gender": "M",
            "physician_reading": "Dr. autumn mud",
            "physician_referring": "Dr. dawn field"
        },
        {
            "patient_id": "cookie-56",
            "patient_name": "fancy tooth",
            "operator_name": "misty mode",
            "patient_gender": "M",
            "physician_reading": "Dr. nameless mode",
            "physician_referring": "Dr. still pine"
        },
        {
            "patient_id": "cookie-56",
            "patient_name": "fancy tooth",
            "operator_name": "wild voice",
            "patient_gender": "M",
            "physician_reading": "Dr. dry mode",
            "physician_referring": "Dr. soft leaf"
        },
        {
            "patient_id": "cookie-56",
            "patient_name": "fancy tooth",
            "operator_name": "long mud",
            "patient_gender": "M",
            "physician_reading": "Dr. raspy meadow",
            "physician_referring": "Dr. silent hall"
        },
        {
            "patient_id": "cookie-56",
            "patient_name": "fancy tooth",
            "operator_name": "throbbing waterfall",
            "patient_gender": "M",
            "physician_reading": "Dr. plain salad",
            "physician_referring": "Dr. dark moon"
        },
        {
            "patient_id": "cookie-56",
            "patient_name": "fancy tooth",
            "operator_name": "autumn glade",
            "patient_gender": "M",
            "physician_reading": "Dr. small bush",
            "physician_referring": "Dr. super mode"
        },
        {
            "patient_id": "cookie-56",
            "patient_name": "fancy tooth",
            "operator_name": "silent dew",
            "patient_gender": "M",
            "physician_reading": "Dr. little moon",
            "physician_referring": "Dr. round poetry"
        },
        {
            "patient_id": "cookie-56",
            "patient_name": "fancy tooth",
            "operator_name": "rapid night",
            "patient_gender": "M",
            "physician_reading": "Dr. summer darkness",
            "physician_referring": "Dr. spring shadow"
        },
        {
            "patient_id": "cookie-56",
            "patient_name": "fancy tooth",
            "operator_name": "weathered cherry",
            "patient_gender": "M",
            "physician_reading": "Dr. wild forest",
            "physician_referring": "Dr. red water"
        },
        {
            "patient_id": "cookie-56",
            "patient_name": "fancy tooth",
            "operator_name": "lucky math",
            "patient_gender": "M",
            "physician_reading": "Dr. royal mode",
            "physician_referring": "Dr. still feather"
        },
        {
            "patient_id": "cookie-56",
            "patient_name": "fancy tooth",
            "operator_name": "patient voice",
            "patient_gender": "M",
            "physician_reading": "Dr. crimson silence",
            "physician_referring": "Dr. floral pond"
        },
        {
            "patient_id": "cookie-56",
            "patient_name": "fancy tooth",
            "operator_name": "restless hill",
            "patient_gender": "M",
            "physician_reading": "Dr. floral art",
            "physician_referring": "Dr. sparkling recipe"
        },
        {
            "patient_id": "cookie-56",
            "patient_name": "fancy tooth",
            "operator_name": "autumn shadow",
            "patient_gender": "M",
            "physician_reading": "Dr. green flower",
            "physician_referring": "Dr. rough salad"
        },
        {
            "patient_id": "cookie-56",
            "patient_name": "fancy tooth",
            "operator_name": "shiny sea",
            "patient_gender": "M",
            "physician_reading": "Dr. dawn shape",
            "physician_referring": "Dr. shrill lake"
        },
        {
            "patient_id": "cookie-56",
            "patient_name": "fancy tooth",
            "operator_name": "wild term",
            "patient_gender": "M",
            "physician_reading": "Dr. odd darkness",
            "physician_referring": "Dr. patient band"
        },
        {
            "patient_id": "cookie-56",
            "patient_name": "fancy tooth",
            "operator_name": "little sound",
            "patient_gender": "M",
            "physician_reading": "Dr. restless shadow",
            "physician_referring": "Dr. lively salad"
        },
        {
            "patient_id": "cookie-56",
            "patient_name": "fancy tooth",
            "operator_name": "raspy scene",
            "patient_gender": "M",
            "physician_reading": "Dr. throbbing sound",
            "physician_referring": "Dr. broad sun"
        },
        {
            "patient_id": "cookie-56",
            "patient_name": "fancy tooth",
            "operator_name": "sweet river",
            "patient_gender": "M",
            "physician_reading": "Dr. billowing art",
            "physician_referring": "Dr. blue shape"
        },
        {
            "patient_id": "cookie-56",
            "patient_name": "fancy tooth",
            "operator_name": "sweet salad",
            "patient_gender": "M",
            "physician_reading": "Dr. little hill",
            "physician_referring": "Dr. sparkling sun"
        },
        {
            "patient_id": "cookie-56",
            "patient_name": "fancy tooth",
            "operator_name": "spring cell",
            "patient_gender": "M",
            "physician_reading": "Dr. wild water",
            "physician_referring": "Dr. noisy fog"
        },
        {
            "patient_id": "cookie-56",
            "patient_name": "fancy tooth",
            "operator_name": "rapid hall",
            "patient_gender": "M",
            "physician_reading": "Dr. proud pond",
            "physician_referring": "Dr. frosty cell"
        },
        {
            "patient_id": "cookie-56",
            "patient_name": "fancy tooth",
            "operator_name": "black darkness",
            "patient_gender": "M",
            "physician_reading": "Dr. cold salad",
            "physician_referring": "Dr. young art"
        },
        {
            "patient_id": "cookie-56",
            "patient_name": "fancy tooth",
            "operator_name": "jolly butterfly",
            "patient_gender": "M",
            "physician_reading": "Dr. muddy wind",
            "physician_referring": "Dr. icy fog"
        },
        {
            "patient_id": "cookie-56",
            "patient_name": "fancy tooth",
            "operator_name": "floral truth",
            "patient_gender": "M",
            "physician_reading": "Dr. summer haze",
            "physician_referring": "Dr. shy cloud"
        }
    ],
    "cookie-8": [
        {
            "patient_id": "cookie-8",
            "patient_name": "red silence",
            "operator_name": "odd sound",
            "patient_gender": "F",
            "physician_reading": "Dr. winter brook",
            "physician_referring": "Dr. lively wildflower"
        }
    ],
    "cookie-44": [
        {
            "patient_id": "cookie-44",
            "patient_name": "white waterfall",
            "operator_name": "muddy silence",
            "patient_gender": "M",
            "physician_reading": "Dr. wild fire",
            "physician_referring": "Dr. rapid silence"
        },
        {
            "patient_id": "cookie-44",
            "patient_name": "white waterfall",
            "operator_name": "snowy glitter",
            "patient_gender": "M",
            "physician_reading": "Dr. jolly sea",
            "physician_referring": "Dr. broken fog"
        },
        {
            "patient_id": "cookie-44",
            "patient_name": "white waterfall",
            "operator_name": "crimson moon",
            "patient_gender": "M",
            "physician_reading": "Dr. sweet recipe",
            "physician_referring": "Dr. rapid lake"
        },
        {
            "patient_id": "cookie-44",
            "patient_name": "white waterfall",
            "operator_name": "soft leaf",
            "patient_gender": "M",
            "physician_reading": "Dr. solitary firefly",
            "physician_referring": "Dr. twilight smoke"
        },
        {
            "patient_id": "cookie-44",
            "patient_name": "white waterfall",
            "operator_name": "billowing credit",
            "patient_gender": "M",
            "physician_reading": "Dr. tiny credit",
            "physician_referring": "Dr. holy recipe"
        },
        {
            "patient_id": "cookie-44",
            "patient_name": "white waterfall",
            "operator_name": "yellow paper",
            "patient_gender": "M",
            "physician_reading": "Dr. fancy star",
            "physician_referring": "Dr. crimson moon"
        }
    ],
    "cookie-34": [
        {
            "patient_id": "cookie-34",
            "patient_name": "dry unit",
            "operator_name": "shrill recipe",
            "patient_gender": "F",
            "physician_reading": "Dr. rough fire",
            "physician_referring": "Dr. floral bush"
        }
    ],
    "cookie-38": [
        {
            "patient_id": "cookie-38",
            "patient_name": "shrill voice",
            "operator_name": "plain art",
            "patient_gender": "M",
            "physician_reading": "Dr. throbbing band",
            "physician_referring": "Dr. flat wildflower"
        }
    ],
    "cookie-17": [
        {
            "patient_id": "cookie-17",
            "patient_name": "wispy lake",
            "operator_name": "broad star",
            "patient_gender": "M",
            "physician_reading": "Dr. wild violet",
            "physician_referring": "Dr. old bird"
        }
    ],
    "cookie-13": [
        {
            "patient_id": "cookie-13",
            "patient_name": "odd tooth",
            "operator_name": "curly salad",
            "patient_gender": "F",
            "physician_reading": "Dr. sparkling morning",
            "physician_referring": "Dr. round cloud"
        }
    ],
    "cookie-43": [
        {
            "patient_id": "cookie-43",
            "patient_name": "old water",
            "operator_name": "damp water",
            "patient_gender": "M",
            "physician_reading": "Dr. curly bread",
            "physician_referring": "Dr. shrill night"
        },
        {
            "patient_id": "cookie-43",
            "patient_name": "old water",
            "operator_name": "delicate wildflower",
            "patient_gender": "M",
            "physician_reading": "Dr. summer grass",
            "physician_referring": "Dr. red unit"
        },
        {
            "patient_id": "cookie-43",
            "patient_name": "old water",
            "operator_name": "tiny sound",
            "patient_gender": "M",
            "physician_reading": "Dr. falling paper",
            "physician_referring": "Dr. twilight pine"
        },
        {
            "patient_id": "cookie-43",
            "patient_name": "old water",
            "operator_name": "white lake",
            "patient_gender": "M",
            "physician_reading": "Dr. broad pine",
            "physician_referring": "Dr. restless frog"
        },
        {
            "patient_id": "cookie-43",
            "patient_name": "old water",
            "operator_name": "rapid truth",
            "patient_gender": "M",
            "physician_reading": "Dr. bitter surf",
            "physician_referring": "Dr. mute smoke"
        }
    ],
    "cookie-69": [
        {
            "patient_id": "cookie-69",
            "patient_name": "damp dream",
            "operator_name": "flat scene",
            "patient_gender": "M",
            "physician_reading": "Dr. long heart",
            "physician_referring": "Dr. solitary dust"
        },
        {
            "patient_id": "cookie-69",
            "patient_name": "damp dream",
            "operator_name": "lively bread",
            "patient_gender": "M",
            "physician_reading": "Dr. dawn hall",
            "physician_referring": "Dr. soft darkness"
        },
        {
            "patient_id": "cookie-69",
            "patient_name": "damp dream",
            "operator_name": "bold hill",
            "patient_gender": "M",
            "physician_reading": "Dr. shy bush",
            "physician_referring": "Dr. wispy sun"
        }
    ],
    "cookie-6": [
        {
            "patient_id": "cookie-6",
            "patient_name": "spring hill",
            "operator_name": "odd glitter",
            "patient_gender": "M",
            "physician_reading": "Dr. old union",
            "physician_referring": "Dr. dark block"
        }
    ],
    "cookie-57": [
        {
            "patient_id": "cookie-57",
            "patient_name": "little paper",
            "operator_name": "late art",
            "patient_gender": "F",
            "physician_reading": "Dr. still lab",
            "physician_referring": "Dr. shrill lab"
        },
        {
            "patient_id": "cookie-57",
            "patient_name": "little paper",
            "operator_name": "divine wave",
            "patient_gender": "F",
            "physician_reading": "Dr. twilight mouse",
            "physician_referring": "Dr. polished breeze"
        },
        {
            "patient_id": "cookie-57",
            "patient_name": "little paper",
            "operator_name": "aged union",
            "patient_gender": "F",
            "physician_reading": "Dr. jolly dawn",
            "physician_referring": "Dr. restless wood"
        },
        {
            "patient_id": "cookie-57",
            "patient_name": "little paper",
            "operator_name": "icy sunset",
            "patient_gender": "F",
            "physician_reading": "Dr. still base",
            "physician_referring": "Dr. quiet forest"
        },
        {
            "patient_id": "cookie-57",
            "patient_name": "little paper",
            "operator_name": "rough mud",
            "patient_gender": "F",
            "physician_reading": "Dr. silent tooth",
            "physician_referring": "Dr. cold star"
        },
        {
            "patient_id": "cookie-57",
            "patient_name": "little paper",
            "operator_name": "sparkling star",
            "patient_gender": "F",
            "physician_reading": "Dr. little wildflower",
            "physician_referring": "Dr. cold bread"
        },
        {
            "patient_id": "cookie-57",
            "patient_name": "little paper",
            "operator_name": "patient math",
            "patient_gender": "F",
            "physician_reading": "Dr. lively violet",
            "physician_referring": "Dr. tiny band"
        },
        {
            "patient_id": "cookie-57",
            "patient_name": "little paper",
            "operator_name": "red silence",
            "patient_gender": "F",
            "physician_reading": "Dr. red scene",
            "physician_referring": "Dr. falling snowflake"
        },
        {
            "patient_id": "cookie-57",
            "patient_name": "little paper",
            "operator_name": "icy math",
            "patient_gender": "F",
            "physician_reading": "Dr. super smoke",
            "physician_referring": "Dr. odd band"
        },
        {
            "patient_id": "cookie-57",
            "patient_name": "little paper",
            "operator_name": "patient bread",
            "patient_gender": "F",
            "physician_reading": "Dr. winter dust",
            "physician_referring": "Dr. solitary cherry"
        },
        {
            "patient_id": "cookie-57",
            "patient_name": "little paper",
            "operator_name": "broken dew",
            "patient_gender": "F",
            "physician_reading": "Dr. still river",
            "physician_referring": "Dr. lingering violet"
        },
        {
            "patient_id": "cookie-57",
            "patient_name": "little paper",
            "operator_name": "raspy rain",
            "patient_gender": "F",
            "physician_reading": "Dr. hidden moon",
            "physician_referring": "Dr. calm salad"
        },
        {
            "patient_id": "cookie-57",
            "patient_name": "little paper",
            "operator_name": "noisy union",
            "patient_gender": "F",
            "physician_reading": "Dr. divine snow",
            "physician_referring": "Dr. sweet frog"
        }
    ],
    "cookie-5": [
        {
            "patient_id": "cookie-5",
            "patient_name": "jolly resonance",
            "operator_name": "spring star",
            "patient_gender": "M",
            "physician_reading": "Dr. patient wildflower",
            "physician_referring": "Dr. tiny truth"
        }
    ],
    "cookie-39": [
        {
            "patient_id": "cookie-39",
            "patient_name": "winter sun",
            "operator_name": "floral glitter",
            "patient_gender": "F",
            "physician_reading": "Dr. restless forest",
            "physician_referring": "Dr. dawn band"
        },
        {
            "patient_id": "cookie-39",
            "patient_name": "winter sun",
            "operator_name": "autumn mountain",
            "patient_gender": "F",
            "physician_reading": "Dr. gentle moon",
            "physician_referring": "Dr. fragrant bonus"
        },
        {
            "patient_id": "cookie-39",
            "patient_name": "winter sun",
            "operator_name": "bitter block",
            "patient_gender": "F",
            "physician_reading": "Dr. sparkling feather",
            "physician_referring": "Dr. round leaf"
        },
        {
            "patient_id": "cookie-39",
            "patient_name": "winter sun",
            "operator_name": "icy snow",
            "patient_gender": "F",
            "physician_reading": "Dr. still water",
            "physician_referring": "Dr. shrill dream"
        },
        {
            "patient_id": "cookie-39",
            "patient_name": "winter sun",
            "operator_name": "purple cell",
            "patient_gender": "F",
            "physician_reading": "Dr. round scene",
            "physician_referring": "Dr. black brook"
        },
        {
            "patient_id": "cookie-39",
            "patient_name": "winter sun",
            "operator_name": "summer sound",
            "patient_gender": "F",
            "physician_reading": "Dr. sweet bonus",
            "physician_referring": "Dr. spring paper"
        },
        {
            "patient_id": "cookie-39",
            "patient_name": "winter sun",
            "operator_name": "bitter cell",
            "patient_gender": "F",
            "physician_reading": "Dr. frosty forest",
            "physician_referring": "Dr. frosty cake"
        },
        {
            "patient_id": "cookie-39",
            "patient_name": "winter sun",
            "operator_name": "green rain",
            "patient_gender": "F",
            "physician_reading": "Dr. gentle mouse",
            "physician_referring": "Dr. bitter cell"
        }
    ],
    "cookie-37": [
        {
            "patient_id": "cookie-37",
            "patient_name": "little art",
            "operator_name": "divine hat",
            "patient_gender": "F",
            "physician_reading": "Dr. hidden cloud",
            "physician_referring": "Dr. frosty hill"
        }
    ],
    "cookie-24": [
        {
            "patient_id": "cookie-24",
            "patient_name": "royal fog",
            "operator_name": "lucky fog",
            "patient_gender": "M",
            "physician_reading": "Dr. spring dew",
            "physician_referring": "Dr. mute star"
        }
    ],
    "cookie-55": [
        {
            "patient_id": "cookie-55",
            "patient_name": "patient wildflower",
            "operator_name": "broken meadow",
            "patient_gender": "F",
            "physician_reading": "Dr. icy butterfly",
            "physician_referring": "Dr. blue river"
        },
        {
            "patient_id": "cookie-55",
            "patient_name": "patient wildflower",
            "operator_name": "purple cherry",
            "patient_gender": "F",
            "physician_reading": "Dr. sparkling recipe",
            "physician_referring": "Dr. broad scene"
        },
        {
            "patient_id": "cookie-55",
            "patient_name": "patient wildflower",
            "operator_name": "small dew",
            "patient_gender": "F",
            "physician_reading": "Dr. noisy bush",
            "physician_referring": "Dr. proud forest"
        },
        {
            "patient_id": "cookie-55",
            "patient_name": "patient wildflower",
            "operator_name": "restless voice",
            "patient_gender": "F",
            "physician_reading": "Dr. curly fire",
            "physician_referring": "Dr. misty tooth"
        },
        {
            "patient_id": "cookie-55",
            "patient_name": "patient wildflower",
            "operator_name": "silent pine",
            "patient_gender": "F",
            "physician_reading": "Dr. dawn star",
            "physician_referring": "Dr. purple river"
        },
        {
            "patient_id": "cookie-55",
            "patient_name": "patient wildflower",
            "operator_name": "lively truth",
            "patient_gender": "F",
            "physician_reading": "Dr. solitary pond",
            "physician_referring": "Dr. twilight cloud"
        }
    ],
    "cookie-63": [
        {
            "patient_id": "cookie-63",
            "patient_name": "odd mountain",
            "operator_name": "weathered dream",
            "patient_gender": "M",
            "physician_reading": "Dr. odd bonus",
            "physician_referring": "Dr. steep king"
        },
        {
            "patient_id": "cookie-63",
            "patient_name": "odd mountain",
            "operator_name": "small hall",
            "patient_gender": "M",
            "physician_reading": "Dr. rapid morning",
            "physician_referring": "Dr. blue surf"
        },
        {
            "patient_id": "cookie-63",
            "patient_name": "odd mountain",
            "operator_name": "super recipe",
            "patient_gender": "M",
            "physician_reading": "Dr. wispy sound",
            "physician_referring": "Dr. morning frog"
        },
        {
            "patient_id": "cookie-63",
            "patient_name": "odd mountain",
            "operator_name": "nameless mountain",
            "patient_gender": "M",
            "physician_reading": "Dr. withered breeze",
            "physician_referring": "Dr. divine wave"
        }
    ],
    "cookie-27": [
        {
            "patient_id": "cookie-27",
            "patient_name": "solitary heart",
            "operator_name": "plain hat",
            "patient_gender": "M",
            "physician_reading": "Dr. aged firefly",
            "physician_referring": "Dr. green paper"
        }
    ],
    "cookie-21": [
        {
            "patient_id": "cookie-21",
            "patient_name": "rough flower",
            "operator_name": "tiny lake",
            "patient_gender": "F",
            "physician_reading": "Dr. dawn pine",
            "physician_referring": "Dr. lingering lake"
        }
    ],
    "cookie-14": [
        {
            "patient_id": "cookie-14",
            "patient_name": "sweet disk",
            "operator_name": "late feather",
            "patient_gender": "M",
            "physician_reading": "Dr. bold poetry",
            "physician_referring": "Dr. lingering mud"
        }
    ],
    "cookie-48": [
        {
            "patient_id": "cookie-48",
            "patient_name": "tight thunder",
            "operator_name": "purple bread",
            "patient_gender": "M",
            "physician_reading": "Dr. patient firefly",
            "physician_referring": "Dr. jolly star"
        },
        {
            "patient_id": "cookie-48",
            "patient_name": "tight thunder",
            "operator_name": "ancient lake",
            "patient_gender": "M",
            "physician_reading": "Dr. mute mode",
            "physician_referring": "Dr. red cloud"
        },
        {
            "patient_id": "cookie-48",
            "patient_name": "tight thunder",
            "operator_name": "dark truth",
            "patient_gender": "M",
            "physician_reading": "Dr. quiet bird",
            "physician_referring": "Dr. aged snowflake"
        },
        {
            "patient_id": "cookie-48",
            "patient_name": "tight thunder",
            "operator_name": "quiet king",
            "patient_gender": "M",
            "physician_reading": "Dr. muddy resonance",
            "physician_referring": "Dr. dry sound"
        },
        {
            "patient_id": "cookie-48",
            "patient_name": "tight thunder",
            "operator_name": "silent block",
            "patient_gender": "M",
            "physician_reading": "Dr. shrill sun",
            "physician_referring": "Dr. tight snowflake"
        },
        {
            "patient_id": "cookie-48",
            "patient_name": "tight thunder",
            "operator_name": "super pond",
            "patient_gender": "M",
            "physician_reading": "Dr. square bar",
            "physician_referring": "Dr. lucky salad"
        },
        {
            "patient_id": "cookie-48",
            "patient_name": "tight thunder",
            "operator_name": "summer disk",
            "patient_gender": "M",
            "physician_reading": "Dr. broad flower",
            "physician_referring": "Dr. fragrant scene"
        },
        {
            "patient_id": "cookie-48",
            "patient_name": "tight thunder",
            "operator_name": "summer dream",
            "patient_gender": "M",
            "physician_reading": "Dr. aged limit",
            "physician_referring": "Dr. fragrant lake"
        }
    ],
    "cookie-36": [
        {
            "patient_id": "cookie-36",
            "patient_name": "young scene",
            "operator_name": "square wildflower",
            "patient_gender": "F",
            "physician_reading": "Dr. late bonus",
            "physician_referring": "Dr. gentle dawn"
        }
    ],
    "cookie-2": [
        {
            "patient_id": "cookie-2",
            "patient_name": "winter night",
            "operator_name": "blue firefly",
            "patient_gender": "M",
            "physician_reading": "Dr. lively river",
            "physician_referring": "Dr. broken mouse"
        }
    ],
    "cookie-26": [
        {
            "patient_id": "cookie-26",
            "patient_name": "damp pine",
            "operator_name": "odd waterfall",
            "patient_gender": "F",
            "physician_reading": "Dr. soft sun",
            "physician_referring": "Dr. proud hill"
        }
    ],
    "cookie-65": [
        {
            "patient_id": "cookie-65",
            "patient_name": "bold art",
            "operator_name": "summer truth",
            "patient_gender": "F",
            "physician_reading": "Dr. damp rain",
            "physician_referring": "Dr. proud base"
        },
        {
            "patient_id": "cookie-65",
            "patient_name": "bold art",
            "operator_name": "shiny bread",
            "patient_gender": "F",
            "physician_reading": "Dr. silent bar",
            "physician_referring": "Dr. icy bread"
        },
        {
            "patient_id": "cookie-65",
            "patient_name": "bold art",
            "operator_name": "delicate morning",
            "patient_gender": "F",
            "physician_reading": "Dr. yellow shadow",
            "physician_referring": "Dr. broad water"
        },
        {
            "patient_id": "cookie-65",
            "patient_name": "bold art",
            "operator_name": "red moon",
            "patient_gender": "F",
            "physician_reading": "Dr. patient surf",
            "physician_referring": "Dr. round poetry"
        },
        {
            "patient_id": "cookie-65",
            "patient_name": "bold art",
            "operator_name": "nameless thunder",
            "patient_gender": "F",
            "physician_reading": "Dr. falling resonance",
            "physician_referring": "Dr. square sun"
        }
    ],
    "cookie-9": [
        {
            "patient_id": "cookie-9",
            "patient_name": "rapid math",
            "operator_name": "mute math",
            "patient_gender": "F",
            "physician_reading": "Dr. restless pine",
            "physician_referring": "Dr. mute dust"
        }
    ],
    "cookie-49": [
        {
            "patient_id": "cookie-49",
            "patient_name": "black boat",
            "operator_name": "noisy cloud",
            "patient_gender": "M",
            "physician_reading": "Dr. damp glitter",
            "physician_referring": "Dr. red king"
        },
        {
            "patient_id": "cookie-49",
            "patient_name": "black boat",
            "operator_name": "long mouse",
            "patient_gender": "M",
            "physician_reading": "Dr. late cake",
            "physician_referring": "Dr. cold lab"
        },
        {
            "patient_id": "cookie-49",
            "patient_name": "black boat",
            "operator_name": "frosty sun",
            "patient_gender": "M",
            "physician_reading": "Dr. soft disk",
            "physician_referring": "Dr. flat dawn"
        },
        {
            "patient_id": "cookie-49",
            "patient_name": "black boat",
            "operator_name": "winter bird",
            "patient_gender": "M",
            "physician_reading": "Dr. green darkness",
            "physician_referring": "Dr. broad cloud"
        },
        {
            "patient_id": "cookie-49",
            "patient_name": "black boat",
            "operator_name": "broken cake",
            "patient_gender": "M",
            "physician_reading": "Dr. black night",
            "physician_referring": "Dr. plain truth"
        },
        {
            "patient_id": "cookie-49",
            "patient_name": "black boat",
            "operator_name": "floral math",
            "patient_gender": "M",
            "physician_reading": "Dr. old field",
            "physician_referring": "Dr. delicate voice"
        },
        {
            "patient_id": "cookie-49",
            "patient_name": "black boat",
            "operator_name": "gentle snow",
            "patient_gender": "M",
            "physician_reading": "Dr. broad dawn",
            "physician_referring": "Dr. curly flower"
        },
        {
            "patient_id": "cookie-49",
            "patient_name": "black boat",
            "operator_name": "nameless cake",
            "patient_gender": "M",
            "physician_reading": "Dr. calm surf",
            "physician_referring": "Dr. proud cloud"
        }
    ],
    "cookie-15": [
        {
            "patient_id": "cookie-15",
            "patient_name": "bold snowflake",
            "operator_name": "orange poetry",
            "patient_gender": "M",
            "physician_reading": "Dr. yellow boat",
            "physician_referring": "Dr. dark sound"
        }
    ],
    "cookie-47": [
        {
            "patient_id": "cookie-47",
            "patient_name": "lingering disk",
            "operator_name": "rapid voice",
            "patient_gender": "F",
            "physician_reading": "Dr. delicate wind",
            "physician_referring": "Dr. spring grass"
        },
        {
            "patient_id": "cookie-47",
            "patient_name": "lingering disk",
            "operator_name": "ancient dawn",
            "patient_gender": "F",
            "physician_reading": "Dr. winter smoke",
            "physician_referring": "Dr. rough fire"
        },
        {
            "patient_id": "cookie-47",
            "patient_name": "lingering disk",
            "operator_name": "flat tooth",
            "patient_gender": "F",
            "physician_reading": "Dr. spring mode",
            "physician_referring": "Dr. rapid shape"
        },
        {
            "patient_id": "cookie-47",
            "patient_name": "lingering disk",
            "operator_name": "winter waterfall",
            "patient_gender": "F",
            "physician_reading": "Dr. patient hall",
            "physician_referring": "Dr. floral darkness"
        },
        {
            "patient_id": "cookie-47",
            "patient_name": "lingering disk",
            "operator_name": "rough lake",
            "patient_gender": "F",
            "physician_reading": "Dr. fancy term",
            "physician_referring": "Dr. raspy block"
        },
        {
            "patient_id": "cookie-47",
            "patient_name": "lingering disk",
            "operator_name": "raspy firefly",
            "patient_gender": "F",
            "physician_reading": "Dr. calm glade",
            "physician_referring": "Dr. proud tree"
        },
        {
            "patient_id": "cookie-47",
            "patient_name": "lingering disk",
            "operator_name": "weathered moon",
            "patient_gender": "F",
            "physician_reading": "Dr. wandering field",
            "physician_referring": "Dr. blue base"
        }
    ],
    "cookie-31": [
        {
            "patient_id": "cookie-31",
            "patient_name": "fragrant limit",
            "operator_name": "dawn silence",
            "patient_gender": "F",
            "physician_reading": "Dr. crimson dawn",
            "physician_referring": "Dr. black wildflower"
        }
    ],
    "cookie-40": [
        {
            "patient_id": "cookie-40",
            "patient_name": "twilight salad",
            "operator_name": "plain wood",
            "patient_gender": "F",
            "physician_reading": "Dr. dry lake",
            "physician_referring": "Dr. royal haze"
        },
        {
            "patient_id": "cookie-40",
            "patient_name": "twilight salad",
            "operator_name": "plain block",
            "patient_gender": "F",
            "physician_reading": "Dr. calm snowflake",
            "physician_referring": "Dr. red leaf"
        },
        {
            "patient_id": "cookie-40",
            "patient_name": "twilight salad",
            "operator_name": "aged hat",
            "patient_gender": "F",
            "physician_reading": "Dr. polished bird",
            "physician_referring": "Dr. rough credit"
        },
        {
            "patient_id": "cookie-40",
            "patient_name": "twilight salad",
            "operator_name": "snowy lab",
            "patient_gender": "F",
            "physician_reading": "Dr. dark truth",
            "physician_referring": "Dr. dark fog"
        },
        {
            "patient_id": "cookie-40",
            "patient_name": "twilight salad",
            "operator_name": "floral bush",
            "patient_gender": "F",
            "physician_reading": "Dr. calm snow",
            "physician_referring": "Dr. damp mud"
        },
        {
            "patient_id": "cookie-40",
            "patient_name": "twilight salad",
            "operator_name": "green unit",
            "patient_gender": "F",
            "physician_reading": "Dr. fancy night",
            "physician_referring": "Dr. lucky thunder"
        }
    ],
    "cookie-35": [
        {
            "patient_id": "cookie-35",
            "patient_name": "holy river",
            "operator_name": "wild dawn",
            "patient_gender": "M",
            "physician_reading": "Dr. gentle flower",
            "physician_referring": "Dr. yellow cherry"
        }
    ],
    "cookie-52": [
        {
            "patient_id": "cookie-52",
            "patient_name": "cool cake",
            "operator_name": "cold queen",
            "patient_gender": "M",
            "physician_reading": "Dr. raspy paper",
            "physician_referring": "Dr. red river"
        },
        {
            "patient_id": "cookie-52",
            "patient_name": "cool cake",
            "operator_name": "rapid rice",
            "patient_gender": "M",
            "physician_reading": "Dr. sparkling art",
            "physician_referring": "Dr. lingering moon"
        },
        {
            "patient_id": "cookie-52",
            "patient_name": "cool cake",
            "operator_name": "plain brook",
            "patient_gender": "M",
            "physician_reading": "Dr. curly sun",
            "physician_referring": "Dr. crimson rice"
        },
        {
            "patient_id": "cookie-52",
            "patient_name": "cool cake",
            "operator_name": "throbbing surf",
            "patient_gender": "M",
            "physician_reading": "Dr. super art",
            "physician_referring": "Dr. broad morning"
        },
        {
            "patient_id": "cookie-52",
            "patient_name": "cool cake",
            "operator_name": "cold field",
            "patient_gender": "M",
            "physician_reading": "Dr. royal shadow",
            "physician_referring": "Dr. dark pond"
        },
        {
            "patient_id": "cookie-52",
            "patient_name": "cool cake",
            "operator_name": "purple flower",
            "patient_gender": "M",
            "physician_reading": "Dr. delicate mud",
            "physician_referring": "Dr. solitary king"
        },
        {
            "patient_id": "cookie-52",
            "patient_name": "cool cake",
            "operator_name": "sweet pine",
            "patient_gender": "M",
            "physician_reading": "Dr. bitter sea",
            "physician_referring": "Dr. shiny mouse"
        }
    ]
}